dfops/__init__.py
dfops/__main__.py
dfops/_internal/__init__.py
dfops/_internal/cli/__init__.py
dfops/_internal/cli/commands/__init__.py
dfops/_internal/cli/commands/help.py
dfops/_internal/cli/commands/run.py
dfops/_internal/cli/commands/version.py
dfops/_internal/cli/io/__init__.py
dfops/_internal/cli/io/argparse.py
dfops/_internal/cli/io/command.py
dfops/_internal/cli/io/inputs/__init__.py
dfops/_internal/cli/io/inputs/argument.py
dfops/_internal/cli/main.py
dfops/_internal/config/__init__.py
dfops/_internal/config/config.py
dfops/_internal/constants.py
dfops/_internal/types/__init__.py
dfops/_internal/types/compat.py
dfops/_internal/utils/__init__.py
dfops/_internal/utils/exe.py
dfops/_internal/utils/git.py
dfops/_internal/utils/misc.py
dfops-0.1.0.dist-info/entry_points.txt
dfops-0.1.0.dist-info/WHEEL
dfops-0.1.0.dist-info/METADATA
dfops-0.1.0.dist-info/RECORD
