Metadata-Version: 2.1
Name: dfops
Version: 0.1.0
Summary: 
Author: Aviv Brook
Author-email: avivbrook@gmail.com
Requires-Python: >=3.8,<4.0
Classifier: Programming Language :: Python :: 3
Classifier: Programming Language :: Python :: 3.10
Classifier: Programming Language :: Python :: 3.8
Classifier: Programming Language :: Python :: 3.9
Requires-Dist: PyYAML (>=6.0,<7.0)
Requires-Dist: identify (>=2.4.12,<3.0.0)
